create_ascii/__init__.py
create_ascii/ascii_image.py
create_ascii/command_line.py
create_ascii/util.py
create_ascii/assets/courier.ttf
create_ascii-0.0.1.dist-info/LICENSE
create_ascii-0.0.1.dist-info/METADATA
create_ascii-0.0.1.dist-info/WHEEL
create_ascii-0.0.1.dist-info/entry_points.txt
create_ascii-0.0.1.dist-info/top_level.txt
create_ascii-0.0.1.dist-info/RECORD
